pytorch2tikz/README.md
pytorch2tikz/__init__.py
pytorch2tikz/arch.py
pytorch2tikz/constants.py
pytorch2tikz/mapping.py
pytorch2tikz/module_graph.py
pytorch2tikz/utils.py
pytorch2tikz/block/D1.py
pytorch2tikz/block/D2.py
pytorch2tikz/block/D3.py
pytorch2tikz/block/Dn.py
pytorch2tikz/block/__init__.py
pytorch2tikz/block/abcs.py
pytorch2tikz/block/connections.py
pytorch2tikz/block/factory.py
pytorch2tikz/block/inputs.py
pytorch2tikz/block/sequence.py
pytorch2tikz/block/tex.py
pytorch2tikz-0.0.1.dist-info/LICENSE
pytorch2tikz-0.0.1.dist-info/WHEEL
pytorch2tikz-0.0.1.dist-info/METADATA
pytorch2tikz-0.0.1.dist-info/RECORD
