Metadata-Version: 2.1
Name: pytorch2tikz
Version: 0.0.1
Summary: Simple tool to generate a tikz figure of a pytorch module by executing it.
Author-email: Jannes Magnusson <jannes@magnusson.berlin>
